{
  "generated_at": "2026-07-16T11:04:41.897780+00:00",
  "kaynak": "CoinMarketCap",
  "coins": [
    {
      "symbol": "BTC",
      "name": "Bitcoin",
      "rank": 1,
      "price_usd": 64142.50538938027,
      "market_cap_usd": 1286512003420.2852,
      "spot_volume_24h_usd": 32497784867.566895,
      "percent_change_7d": 2.22499194
    },
    {
      "symbol": "ETH",
      "name": "Ethereum",
      "rank": 2,
      "price_usd": 1886.0942251748597,
      "market_cap_usd": 227619345150.7358,
      "spot_volume_24h_usd": 13852016190.540323,
      "percent_change_7d": 8.06912601
    },
    {
      "symbol": "USDT",
      "name": "Tether USDt",
      "rank": 3,
      "price_usd": 0.999116659520897,
      "market_cap_usd": 184188985258.95667,
      "spot_volume_24h_usd": 63596658594.27198,
      "percent_change_7d": 0.00582478
    },
    {
      "symbol": "BNB",
      "name": "BNB",
      "rank": 4,
      "price_usd": 577.0560597521435,
      "market_cap_usd": 76844297116.36806,
      "spot_volume_24h_usd": 1135778866.5515692,
      "percent_change_7d": 1.3173847
    },
    {
      "symbol": "USDC",
      "name": "USDC",
      "rank": 5,
      "price_usd": 0.9998552036055004,
      "market_cap_usd": 73081221046.3725,
      "spot_volume_24h_usd": 10139827997.53352,
      "percent_change_7d": 0.00753265
    },
    {
      "symbol": "XRP",
      "name": "XRP",
      "rank": 6,
      "price_usd": 1.1073131782205894,
      "market_cap_usd": 69169982747.69714,
      "spot_volume_24h_usd": 1232300756.7522123,
      "percent_change_7d": 1.48532049
    },
    {
      "symbol": "SOL",
      "name": "Solana",
      "rank": 7,
      "price_usd": 76.117934657503,
      "market_cap_usd": 44331798612.38389,
      "spot_volume_24h_usd": 2125210199.878753,
      "percent_change_7d": -1.95536159
    },
    {
      "symbol": "TRX",
      "name": "TRON",
      "rank": 8,
      "price_usd": 0.32334887738209483,
      "market_cap_usd": 30675594928.521427,
      "spot_volume_24h_usd": 516361616.6637324,
      "percent_change_7d": -2.40043937
    },
    {
      "symbol": "HYPE",
      "name": "Hyperliquid",
      "rank": 9,
      "price_usd": 65.8659746320193,
      "market_cap_usd": 16660751664.13559,
      "spot_volume_24h_usd": 409611619.50770587,
      "percent_change_7d": -2.34754174
    },
    {
      "symbol": "DOGE",
      "name": "Dogecoin",
      "rank": 10,
      "price_usd": 0.07323418461285904,
      "market_cap_usd": 12508738767.465397,
      "spot_volume_24h_usd": 577944806.7457803,
      "percent_change_7d": 1.25075193
    },
    {
      "symbol": "ZEC",
      "name": "Zcash",
      "rank": 11,
      "price_usd": 547.4647392169884,
      "market_cap_usd": 9183239322.02441,
      "spot_volume_24h_usd": 640692737.2317594,
      "percent_change_7d": 17.35472155
    },
    {
      "symbol": "LEO",
      "name": "UNUS SED LEO",
      "rank": 12,
      "price_usd": 9.815662590559603,
      "market_cap_usd": 9032268187.860453,
      "spot_volume_24h_usd": 307351.02687298,
      "percent_change_7d": 3.20173097
    },
    {
      "symbol": "XLM",
      "name": "Stellar",
      "rank": 13,
      "price_usd": 0.18863807940341165,
      "market_cap_usd": 6448947991.86878,
      "spot_volume_24h_usd": 225827526.9610019,
      "percent_change_7d": 4.55822231
    },
    {
      "symbol": "LINK",
      "name": "Chainlink",
      "rank": 14,
      "price_usd": 8.433216228939369,
      "market_cap_usd": 6308888811.456193,
      "spot_volume_24h_usd": 278532717.4236858,
      "percent_change_7d": 9.20749322
    },
    {
      "symbol": "XMR",
      "name": "Monero",
      "rank": 15,
      "price_usd": 334.2967438921165,
      "market_cap_usd": 6277629245.384468,
      "spot_volume_24h_usd": 94521807.01173036,
      "percent_change_7d": 4.59716093
    },
    {
      "symbol": "ADA",
      "name": "Cardano",
      "rank": 16,
      "price_usd": 0.16228628789803154,
      "market_cap_usd": 5919787965.055358,
      "spot_volume_24h_usd": 305209084.44462293,
      "percent_change_7d": -3.53037222
    },
    {
      "symbol": "CC",
      "name": "Canton",
      "rank": 17,
      "price_usd": 0.13267851859292476,
      "market_cap_usd": 5185482695.200233,
      "spot_volume_24h_usd": 36673574.00498017,
      "percent_change_7d": 4.07622839
    },
    {
      "symbol": "DAI",
      "name": "Dai",
      "rank": 18,
      "price_usd": 0.9996532022472078,
      "market_cap_usd": 4648859848.379825,
      "spot_volume_24h_usd": 44773160.16344728,
      "percent_change_7d": -0.00102619
    },
    {
      "symbol": "BCH",
      "name": "Bitcoin Cash",
      "rank": 19,
      "price_usd": 220.77726079793328,
      "market_cap_usd": 4429225126.980858,
      "spot_volume_24h_usd": 206979540.50328714,
      "percent_change_7d": -6.52967897
    },
    {
      "symbol": "USD1",
      "name": "World Liberty Financial USD",
      "rank": 20,
      "price_usd": 0.9987324088532762,
      "market_cap_usd": 4309196601.600702,
      "spot_volume_24h_usd": 1000114138.4821677,
      "percent_change_7d": -0.01287202
    },
    {
      "symbol": "GRAM",
      "name": "Gram (prev. Toncoin)",
      "rank": 21,
      "price_usd": 1.5558742639673677,
      "market_cap_usd": 4244056541.854369,
      "spot_volume_24h_usd": 57161027.30605453,
      "percent_change_7d": -2.05800306
    },
    {
      "symbol": "USDE",
      "name": "Ethena USDe",
      "rank": 22,
      "price_usd": 0.9997200120149069,
      "market_cap_usd": 4015264940.278628,
      "spot_volume_24h_usd": 74433259.96198347,
      "percent_change_7d": 0.06321312
    },
    {
      "symbol": "LTC",
      "name": "Litecoin",
      "rank": 23,
      "price_usd": 44.64283036696767,
      "market_cap_usd": 3455048882.2003584,
      "spot_volume_24h_usd": 282723447.93540496,
      "percent_change_7d": 2.06653943
    },
    {
      "symbol": "USDG",
      "name": "Global Dollar",
      "rank": 24,
      "price_usd": 0.9999197424895523,
      "market_cap_usd": 3159217548.668054,
      "spot_volume_24h_usd": 184442146.22878635,
      "percent_change_7d": 0.00262907
    },
    {
      "symbol": "SUI",
      "name": "Sui",
      "rank": 25,
      "price_usd": 0.7416172299769725,
      "market_cap_usd": 3005280779.312676,
      "spot_volume_24h_usd": 253262514.13702846,
      "percent_change_7d": 2.93778618
    },
    {
      "symbol": "HBAR",
      "name": "Hedera",
      "rank": 26,
      "price_usd": 0.067228554410393,
      "market_cap_usd": 2944012096.8112063,
      "spot_volume_24h_usd": 45924615.71936893,
      "percent_change_7d": -4.40077145
    },
    {
      "symbol": "DEXE",
      "name": "DeXe",
      "rank": 27,
      "price_usd": 34.97634512500747,
      "market_cap_usd": 2928698194.813422,
      "spot_volume_24h_usd": 125217874.59017651,
      "percent_change_7d": 22.47407024
    },
    {
      "symbol": "PYUSD",
      "name": "PayPal USD",
      "rank": 28,
      "price_usd": 0.9996677264676435,
      "market_cap_usd": 2846681238.3870897,
      "spot_volume_24h_usd": 39281857.59227833,
      "percent_change_7d": 0.0015796
    },
    {
      "symbol": "AVAX",
      "name": "Avalanche",
      "rank": 29,
      "price_usd": 6.587881770474208,
      "market_cap_usd": 2844462632.0412517,
      "spot_volume_24h_usd": 222254022.74823183,
      "percent_change_7d": -1.37046039
    },
    {
      "symbol": "NEAR",
      "name": "NEAR Protocol",
      "rank": 30,
      "price_usd": 2.0286879438077032,
      "market_cap_usd": 2639295134.6354103,
      "spot_volume_24h_usd": 199839335.86655107,
      "percent_change_7d": 6.83968342
    },
    {
      "symbol": "CRO",
      "name": "Cronos",
      "rank": 31,
      "price_usd": 0.0560809141471008,
      "market_cap_usd": 2584732864.7914524,
      "spot_volume_24h_usd": 6368358.29133803,
      "percent_change_7d": -0.45371612
    },
    {
      "symbol": "XAUT",
      "name": "Tether Gold",
      "rank": 32,
      "price_usd": 4023.5332912313297,
      "market_cap_usd": 2465716395.7812157,
      "spot_volume_24h_usd": 152610400.7230522,
      "percent_change_7d": -1.53150369
    },
    {
      "symbol": "SHIB",
      "name": "Shiba Inu",
      "rank": 33,
      "price_usd": 4.161342198872452e-06,
      "market_cap_usd": 2452041471.240645,
      "spot_volume_24h_usd": 53761642.71918415,
      "percent_change_7d": -2.82483692
    },
    {
      "symbol": "UNI",
      "name": "Uniswap",
      "rank": 34,
      "price_usd": 3.716746886386089,
      "market_cap_usd": 2325039119.1606483,
      "spot_volume_24h_usd": 192955799.8434986,
      "percent_change_7d": 10.77524186
    },
    {
      "symbol": "TAO",
      "name": "Bittensor",
      "rank": 35,
      "price_usd": 196.325672969278,
      "market_cap_usd": 2184834186.834409,
      "spot_volume_24h_usd": 146281739.75786796,
      "percent_change_7d": -4.40967425
    },
    {
      "symbol": "WLFI",
      "name": "World Liberty Financial",
      "rank": 36,
      "price_usd": 0.058040993623389,
      "market_cap_usd": 1844223748.4131782,
      "spot_volume_24h_usd": 39406062.31470301,
      "percent_change_7d": -0.09262079
    },
    {
      "symbol": "ONDO",
      "name": "Ondo",
      "rank": 37,
      "price_usd": 0.37300286975283736,
      "market_cap_usd": 1816274305.1064403,
      "spot_volume_24h_usd": 264663852.10031265,
      "percent_change_7d": 17.61801231
    },
    {
      "symbol": "PAXG",
      "name": "PAX Gold",
      "rank": 38,
      "price_usd": 4021.741448526291,
      "market_cap_usd": 1805313638.3874252,
      "spot_volume_24h_usd": 99099080.6716938,
      "percent_change_7d": -1.71702721
    },
    {
      "symbol": "OKB",
      "name": "OKB",
      "rank": 39,
      "price_usd": 81.26887162010648,
      "market_cap_usd": 1706646304.022236,
      "spot_volume_24h_usd": 18158986.87296935,
      "percent_change_7d": 2.11368738
    },
    {
      "symbol": "ASTER",
      "name": "Aster",
      "rank": 40,
      "price_usd": 0.6251108061610859,
      "market_cap_usd": 1687817364.2253869,
      "spot_volume_24h_usd": 58974489.33298008,
      "percent_change_7d": 0.78938339
    },
    {
      "symbol": "M",
      "name": "MemeCore",
      "rank": 41,
      "price_usd": 1.2101987920138526,
      "market_cap_usd": 1602910169.2990844,
      "spot_volume_24h_usd": 16594208.10751989,
      "percent_change_7d": 2.64796962
    },
    {
      "symbol": "RLUSD",
      "name": "Ripple USD",
      "rank": 42,
      "price_usd": 0.9998370562986286,
      "market_cap_usd": 1514561767.480862,
      "spot_volume_24h_usd": 142369363.55436388,
      "percent_change_7d": -0.00319653
    },
    {
      "symbol": "SKY",
      "name": "Sky",
      "rank": 43,
      "price_usd": 0.06292025493782658,
      "market_cap_usd": 1468721461.8179672,
      "spot_volume_24h_usd": 20427928.93650377,
      "percent_change_7d": 9.8240663
    },
    {
      "symbol": "AAVE",
      "name": "Aave",
      "rank": 44,
      "price_usd": 94.61736485922734,
      "market_cap_usd": 1458552005.6393542,
      "spot_volume_24h_usd": 211497667.4979367,
      "percent_change_7d": 6.94874747
    },
    {
      "symbol": "USDD",
      "name": "USDD",
      "rank": 45,
      "price_usd": 0.9991522941385736,
      "market_cap_usd": 1445206526.542396,
      "spot_volume_24h_usd": 25223329.22239668,
      "percent_change_7d": 0.2363757
    },
    {
      "symbol": "MNT",
      "name": "Mantle",
      "rank": 46,
      "price_usd": 0.43601162826331535,
      "market_cap_usd": 1439838750.734687,
      "spot_volume_24h_usd": 34416244.86054079,
      "percent_change_7d": 1.94433301
    },
    {
      "symbol": "DOT",
      "name": "Polkadot",
      "rank": 47,
      "price_usd": 0.8392799703950294,
      "market_cap_usd": 1421343017.9582434,
      "spot_volume_24h_usd": 92761678.43517955,
      "percent_change_7d": 1.24011822
    },
    {
      "symbol": "WLD",
      "name": "Worldcoin",
      "rank": 48,
      "price_usd": 0.39806161295315073,
      "market_cap_usd": 1408575267.7917273,
      "spot_volume_24h_usd": 206208394.59063515,
      "percent_change_7d": 2.96245726
    },
    {
      "symbol": "ICP",
      "name": "Internet Computer",
      "rank": 49,
      "price_usd": 2.1603629332329564,
      "market_cap_usd": 1199172060.735479,
      "spot_volume_24h_usd": 35551613.17699733,
      "percent_change_7d": -3.45396738
    },
    {
      "symbol": "BGB",
      "name": "Bitget Token",
      "rank": 50,
      "price_usd": 1.65818321444464,
      "market_cap_usd": 1158343929.2815256,
      "spot_volume_24h_usd": 13983476.8028328,
      "percent_change_7d": 1.01384382
    },
    {
      "symbol": "PEPE",
      "name": "Pepe",
      "rank": 51,
      "price_usd": 2.7304108239965276e-06,
      "market_cap_usd": 1129768839.1920273,
      "spot_volume_24h_usd": 275080434.20400596,
      "percent_change_7d": 4.33222508
    },
    {
      "symbol": "ETC",
      "name": "Ethereum Classic",
      "rank": 52,
      "price_usd": 6.978059757938931,
      "market_cap_usd": 1099177024.4573348,
      "spot_volume_24h_usd": 31377518.49203289,
      "percent_change_7d": -0.19347696
    },
    {
      "symbol": "MORPHO",
      "name": "Morpho",
      "rank": 53,
      "price_usd": 2.1014420837615804,
      "market_cap_usd": 1084870380.604289,
      "spot_volume_24h_usd": 19247503.47117138,
      "percent_change_7d": 2.17491134
    },
    {
      "symbol": "U",
      "name": "United Stables",
      "rank": 54,
      "price_usd": 0.9996603151399889,
      "market_cap_usd": 1043154644.1545929,
      "spot_volume_24h_usd": 140486493.41423494,
      "percent_change_7d": -0.00256243
    },
    {
      "symbol": "KCS",
      "name": "KuCoin Token",
      "rank": 55,
      "price_usd": 6.811748768858861,
      "market_cap_usd": 934265547.4542843,
      "spot_volume_24h_usd": 2770807.86203284,
      "percent_change_7d": -1.41146313
    },
    {
      "symbol": "STABLE",
      "name": "Stable",
      "rank": 56,
      "price_usd": 0.037715073991980874,
      "market_cap_usd": 925207622.156797,
      "spot_volume_24h_usd": 15378788.81075906,
      "percent_change_7d": 7.7753655
    },
    {
      "symbol": "POL",
      "name": "Polygon (prev. MATIC)",
      "rank": 57,
      "price_usd": 0.08306985185208461,
      "market_cap_usd": 887126539.3197902,
      "spot_volume_24h_usd": 44389334.74030142,
      "percent_change_7d": 8.5866703
    },
    {
      "symbol": "JST",
      "name": "JUST",
      "rank": 58,
      "price_usd": 0.09880058611221018,
      "market_cap_usd": 844128946.8552321,
      "spot_volume_24h_usd": 45044782.79908291,
      "percent_change_7d": 1.973154
    },
    {
      "symbol": "PI",
      "name": "Pi",
      "rank": 59,
      "price_usd": 0.07574071108863148,
      "market_cap_usd": 828735245.676181,
      "spot_volume_24h_usd": 22412271.16686945,
      "percent_change_7d": -22.76872727
    },
    {
      "symbol": "BEAT",
      "name": "Audiera",
      "rank": 60,
      "price_usd": 2.582306618303734,
      "market_cap_usd": 798621358.4325304,
      "spot_volume_24h_usd": 20791304.9685473,
      "percent_change_7d": 18.30564232
    },
    {
      "symbol": "ATOM",
      "name": "Cosmos",
      "rank": 61,
      "price_usd": 1.5346126243968814,
      "market_cap_usd": 797157960.5441,
      "spot_volume_24h_usd": 25310242.06130547,
      "percent_change_7d": -1.8777004
    },
    {
      "symbol": "ENA",
      "name": "Ethena",
      "rank": 62,
      "price_usd": 0.0821455317707787,
      "market_cap_usd": 785388295.1646795,
      "spot_volume_24h_usd": 137025007.92685348,
      "percent_change_7d": 7.35226874
    },
    {
      "symbol": "KAS",
      "name": "Kaspa",
      "rank": 63,
      "price_usd": 0.02844156252017569,
      "market_cap_usd": 784376932.4055183,
      "spot_volume_24h_usd": 9103075.88104234,
      "percent_change_7d": -2.20522053
    },
    {
      "symbol": "QNT",
      "name": "Quant",
      "rank": 64,
      "price_usd": 64.83333089112028,
      "market_cap_usd": 782715817.5158017,
      "spot_volume_24h_usd": 6179902.91843447,
      "percent_change_7d": -1.64247641
    },
    {
      "symbol": "RENDER",
      "name": "Render",
      "rank": 65,
      "price_usd": 1.501194721734041,
      "market_cap_usd": 778777940.2284538,
      "spot_volume_24h_usd": 18567253.71887234,
      "percent_change_7d": -2.89940971
    },
    {
      "symbol": "ALGO",
      "name": "Algorand",
      "rank": 66,
      "price_usd": 0.08328712566136104,
      "market_cap_usd": 746984056.9095367,
      "spot_volume_24h_usd": 23501328.20916548,
      "percent_change_7d": -1.84247309
    },
    {
      "symbol": "币安人生",
      "name": "币安人生",
      "rank": 67,
      "price_usd": 0.7166172515543356,
      "market_cap_usd": 716617251.5543356,
      "spot_volume_24h_usd": 18790216.36330209,
      "percent_change_7d": 3.10572519
    },
    {
      "symbol": "GT",
      "name": "GateToken",
      "rank": 68,
      "price_usd": 6.706921175801602,
      "market_cap_usd": 714683096.9396626,
      "spot_volume_24h_usd": 2796190.15202432,
      "percent_change_7d": -0.8192004
    },
    {
      "symbol": "JUP",
      "name": "Jupiter",
      "rank": 69,
      "price_usd": 0.20255631557218487,
      "market_cap_usd": 672550361.3608303,
      "spot_volume_24h_usd": 24753771.11138256,
      "percent_change_7d": -3.45946123
    },
    {
      "symbol": "PUMP",
      "name": "Pump.fun",
      "rank": 70,
      "price_usd": 0.0016057910309474107,
      "market_cap_usd": 643717235.1670442,
      "spot_volume_24h_usd": 85830442.74100162,
      "percent_change_7d": 6.75595727
    },
    {
      "symbol": "FIL",
      "name": "Filecoin",
      "rank": 71,
      "price_usd": 0.776371412483449,
      "market_cap_usd": 620553420.7827973,
      "spot_volume_24h_usd": 55535453.53557985,
      "percent_change_7d": 0.59732042
    },
    {
      "symbol": "LIT",
      "name": "Lighter",
      "rank": 72,
      "price_usd": 2.3721968159683207,
      "market_cap_usd": 593049203.9920802,
      "spot_volume_24h_usd": 55366928.60315003,
      "percent_change_7d": -4.68859526
    },
    {
      "symbol": "XDC",
      "name": "XDC Network",
      "rank": 73,
      "price_usd": 0.027411125122935396,
      "market_cap_usd": 576002228.614516,
      "spot_volume_24h_usd": 7377326.33976032,
      "percent_change_7d": 1.08668689
    },
    {
      "symbol": "FLR",
      "name": "Flare",
      "rank": 74,
      "price_usd": 0.0065799876673444035,
      "market_cap_usd": 571229065.0442513,
      "spot_volume_24h_usd": 2982353.4691464,
      "percent_change_7d": -0.29229716
    },
    {
      "symbol": "ARB",
      "name": "Arbitrum",
      "rank": 75,
      "price_usd": 0.08672895488089229,
      "market_cap_usd": 551842553.6459076,
      "spot_volume_24h_usd": 69092787.42156464,
      "percent_change_7d": 0.52887027
    },
    {
      "symbol": "APT",
      "name": "Aptos",
      "rank": 76,
      "price_usd": 0.611869664481358,
      "market_cap_usd": 516826832.186713,
      "spot_volume_24h_usd": 45671760.4479059,
      "percent_change_7d": -2.30911975
    },
    {
      "symbol": "INJ",
      "name": "Injective",
      "rank": 77,
      "price_usd": 5.047543989092751,
      "market_cap_usd": 504607790.4703399,
      "spot_volume_24h_usd": 113221826.8860962,
      "percent_change_7d": 4.28829746
    },
    {
      "symbol": "VVV",
      "name": "Venice Token",
      "rank": 78,
      "price_usd": 10.650038541220429,
      "market_cap_usd": 503966918.30914074,
      "spot_volume_24h_usd": 24378180.01345663,
      "percent_change_7d": -5.25966568
    },
    {
      "symbol": "NIGHT",
      "name": "Midnight",
      "rank": 79,
      "price_usd": 0.030109525019849558,
      "market_cap_usd": 500040907.7790441,
      "spot_volume_24h_usd": 14895536.27256484,
      "percent_change_7d": -3.84142518
    },
    {
      "symbol": "TUSD",
      "name": "TrueUSD",
      "rank": 80,
      "price_usd": 0.9974435022036048,
      "market_cap_usd": 493250856.2800263,
      "spot_volume_24h_usd": 34335727.3823194,
      "percent_change_7d": -0.06073928
    },
    {
      "symbol": "NEXO",
      "name": "Nexo",
      "rank": 81,
      "price_usd": 0.7479725458566552,
      "market_cap_usd": 483299348.62136286,
      "spot_volume_24h_usd": 7100460.2828744,
      "percent_change_7d": 1.68436685
    },
    {
      "symbol": "AERO",
      "name": "Aerodrome Finance",
      "rank": 82,
      "price_usd": 0.4937225755627734,
      "market_cap_usd": 478709128.01032615,
      "spot_volume_24h_usd": 22621510.55226028,
      "percent_change_7d": -6.8585835
    },
    {
      "symbol": "CAKE",
      "name": "PancakeSwap",
      "rank": 83,
      "price_usd": 1.395935441103349,
      "market_cap_usd": 450545083.6694803,
      "spot_volume_24h_usd": 26648593.90871662,
      "percent_change_7d": 0.25443008
    },
    {
      "symbol": "DASH",
      "name": "Dash",
      "rank": 84,
      "price_usd": 33.88715008499884,
      "market_cap_usd": 432655770.5455291,
      "spot_volume_24h_usd": 59767474.98363636,
      "percent_change_7d": -0.02020264
    },
    {
      "symbol": "EURC",
      "name": "EURC",
      "rank": 85,
      "price_usd": 1.1457964148961086,
      "market_cap_usd": 427750324.21608967,
      "spot_volume_24h_usd": 54966676.23568962,
      "percent_change_7d": 0.29174396
    },
    {
      "symbol": "VIRTUAL",
      "name": "Virtuals Protocol",
      "rank": 86,
      "price_usd": 0.6377557872441184,
      "market_cap_usd": 419324043.58884895,
      "spot_volume_24h_usd": 97828549.62165846,
      "percent_change_7d": 21.78723982
    },
    {
      "symbol": "VET",
      "name": "VeChain",
      "rank": 87,
      "price_usd": 0.00478367028308017,
      "market_cap_usd": 411324086.26783967,
      "spot_volume_24h_usd": 10789977.98542418,
      "percent_change_7d": 1.6002549
    },
    {
      "symbol": "ETHFI",
      "name": "ether.fi",
      "rank": 88,
      "price_usd": 0.42982206329648087,
      "market_cap_usd": 398602496.0678012,
      "spot_volume_24h_usd": 61352249.31467322,
      "percent_change_7d": 3.20733503
    },
    {
      "symbol": "PYTH",
      "name": "Pyth Network",
      "rank": 89,
      "price_usd": 0.05048281369179611,
      "market_cap_usd": 397551233.0208249,
      "spot_volume_24h_usd": 27684807.83450408,
      "percent_change_7d": 18.82123571
    },
    {
      "symbol": "PENGU",
      "name": "Pudgy Penguins",
      "rank": 90,
      "price_usd": 0.006147590947590387,
      "market_cap_usd": 386440001.9650761,
      "spot_volume_24h_usd": 62291380.10562341,
      "percent_change_7d": -0.26424989
    },
    {
      "symbol": "TIA",
      "name": "Celestia",
      "rank": 91,
      "price_usd": 0.40197531606475434,
      "market_cap_usd": 369790357.07573,
      "spot_volume_24h_usd": 32568565.99094883,
      "percent_change_7d": -0.19696877
    },
    {
      "symbol": "TRUMP",
      "name": "OFFICIAL TRUMP",
      "rank": 92,
      "price_usd": 1.5570466479854608,
      "market_cap_usd": 369663310.12146103,
      "spot_volume_24h_usd": 204551798.43854073,
      "percent_change_7d": -3.28484022
    },
    {
      "symbol": "FET",
      "name": "Artificial Superintelligence Alliance",
      "rank": 93,
      "price_usd": 0.15789502943028116,
      "market_cap_usd": 353752828.87377787,
      "spot_volume_24h_usd": 110114522.9882894,
      "percent_change_7d": -0.79283281
    },
    {
      "symbol": "SEI",
      "name": "Sei",
      "rank": 94,
      "price_usd": 0.047667317163391336,
      "market_cap_usd": 349825144.25118434,
      "spot_volume_24h_usd": 25365559.36088973,
      "percent_change_7d": 0.33876585
    },
    {
      "symbol": "SUN",
      "name": "Sun [New]",
      "rank": 95,
      "price_usd": 0.01801060641188609,
      "market_cap_usd": 346365700.4047724,
      "spot_volume_24h_usd": 63830543.70839375,
      "percent_change_7d": -4.20996489
    },
    {
      "symbol": "FDUSD",
      "name": "First Digital USD",
      "rank": 96,
      "price_usd": 0.9970775240298795,
      "market_cap_usd": 346140978.08350366,
      "spot_volume_24h_usd": 196182938.9557443,
      "percent_change_7d": 0.00711256
    },
    {
      "symbol": "SPX",
      "name": "SPX6900",
      "rank": 97,
      "price_usd": 0.3674177719670127,
      "market_cap_usd": 342063406.8702038,
      "spot_volume_24h_usd": 6962547.29635516,
      "percent_change_7d": -0.99560454
    },
    {
      "symbol": "CRV",
      "name": "Curve DAO Token",
      "rank": 99,
      "price_usd": 0.2134203726682601,
      "market_cap_usd": 326478151.91386545,
      "spot_volume_24h_usd": 43643307.36546078,
      "percent_change_7d": 6.12714583
    },
    {
      "symbol": "LUNC",
      "name": "Terra Classic",
      "rank": 99,
      "price_usd": 5.90420947048867e-05,
      "market_cap_usd": 326423680.13094497,
      "spot_volume_24h_usd": 9956232.46788476,
      "percent_change_7d": -3.74794995
    },
    {
      "symbol": "BONK",
      "name": "Bonk",
      "rank": 100,
      "price_usd": 3.553662931915082e-06,
      "market_cap_usd": 312703161.8887815,
      "spot_volume_24h_usd": 53234848.6670279,
      "percent_change_7d": -11.03090041
    },
    {
      "symbol": "LDO",
      "name": "Lido DAO",
      "rank": 101,
      "price_usd": 0.3639528727842498,
      "market_cap_usd": 304396471.85715127,
      "spot_volume_24h_usd": 75310063.95084152,
      "percent_change_7d": 13.69616552
    },
    {
      "symbol": "GNO",
      "name": "Gnosis",
      "rank": 102,
      "price_usd": 115.23622058214875,
      "market_cap_usd": 304167169.5467432,
      "spot_volume_24h_usd": 9664019.05510306,
      "percent_change_7d": 8.16770975
    },
    {
      "symbol": "STX",
      "name": "Stacks",
      "rank": 103,
      "price_usd": 0.16674939698541882,
      "market_cap_usd": 302584420.9470148,
      "spot_volume_24h_usd": 5333958.89590007,
      "percent_change_7d": -2.11720853
    },
    {
      "symbol": "JTO",
      "name": "Jito",
      "rank": 104,
      "price_usd": 0.5992649320000429,
      "market_cap_usd": 299024408.8327186,
      "spot_volume_24h_usd": 36542730.35017466,
      "percent_change_7d": -6.31983898
    },
    {
      "symbol": "ZRO",
      "name": "LayerZero",
      "rank": 105,
      "price_usd": 0.8102067090819464,
      "market_cap_usd": 286821752.3648033,
      "spot_volume_24h_usd": 30395617.86050725,
      "percent_change_7d": -12.64650619
    },
    {
      "symbol": "PENDLE",
      "name": "Pendle",
      "rank": 106,
      "price_usd": 1.5931245322060026,
      "market_cap_usd": 272661421.8036933,
      "spot_volume_24h_usd": 35675251.40950616,
      "percent_change_7d": -0.04405598
    },
    {
      "symbol": "BTT",
      "name": "BitTorrent [New]",
      "rank": 107,
      "price_usd": 2.7017248257361076e-07,
      "market_cap_usd": 266670476.0117833,
      "spot_volume_24h_usd": 4743948.66653935,
      "percent_change_7d": 1.52658573
    },
    {
      "symbol": "NFT",
      "name": "AINFT",
      "rank": 108,
      "price_usd": 2.675165656994e-07,
      "market_cap_usd": 264869647.9145466,
      "spot_volume_24h_usd": 7370756.50313107,
      "percent_change_7d": -0.19233947
    },
    {
      "symbol": "BSV",
      "name": "Bitcoin SV",
      "rank": 109,
      "price_usd": 13.124811602781048,
      "market_cap_usd": 263238686.24197578,
      "spot_volume_24h_usd": 14829097.86249848,
      "percent_change_7d": -1.54793662
    },
    {
      "symbol": "MON",
      "name": "Monad",
      "rank": 110,
      "price_usd": 0.022199364515074337,
      "market_cap_usd": 262511148.285899,
      "spot_volume_24h_usd": 18235655.52061282,
      "percent_change_7d": -3.72190134
    },
    {
      "symbol": "IMX",
      "name": "Immutable",
      "rank": 111,
      "price_usd": 0.12841807967578373,
      "market_cap_usd": 256836159.35156745,
      "spot_volume_24h_usd": 10004779.52609341,
      "percent_change_7d": -6.91323927
    },
    {
      "symbol": "XTZ",
      "name": "Tezos",
      "rank": 112,
      "price_usd": 0.23034132372174798,
      "market_cap_usd": 251237607.23066282,
      "spot_volume_24h_usd": 10009741.61906711,
      "percent_change_7d": -3.77935696
    },
    {
      "symbol": "DCR",
      "name": "Decred",
      "rank": 113,
      "price_usd": 13.678980670069334,
      "market_cap_usd": 239579743.1165856,
      "spot_volume_24h_usd": 4902847.7627796,
      "percent_change_7d": 25.5497989
    },
    {
      "symbol": "2Z",
      "name": "DoubleZero",
      "rank": 114,
      "price_usd": 0.06835488476065876,
      "market_cap_usd": 237288343.16863412,
      "spot_volume_24h_usd": 5108081.17819416,
      "percent_change_7d": -3.39282242
    },
    {
      "symbol": "CFX",
      "name": "Conflux",
      "rank": 115,
      "price_usd": 0.0448244919726537,
      "market_cap_usd": 234170834.79949313,
      "spot_volume_24h_usd": 7813025.93397069,
      "percent_change_7d": 6.16034409
    },
    {
      "symbol": "OP",
      "name": "Optimism",
      "rank": 116,
      "price_usd": 0.09994966574224866,
      "market_cap_usd": 228060153.20566452,
      "spot_volume_24h_usd": 44786037.07971109,
      "percent_change_7d": -3.67140645
    },
    {
      "symbol": "SYRUP",
      "name": "Maple Finance",
      "rank": 117,
      "price_usd": 0.18801168375438704,
      "market_cap_usd": 223923665.14821464,
      "spot_volume_24h_usd": 23268806.0806922,
      "percent_change_7d": 18.46551504
    },
    {
      "symbol": "XPL",
      "name": "Plasma",
      "rank": 118,
      "price_usd": 0.08578119103766794,
      "market_cap_usd": 223031096.69793665,
      "spot_volume_24h_usd": 78328436.13986176,
      "percent_change_7d": -6.84422461
    },
    {
      "symbol": "KITE",
      "name": "Kite",
      "rank": 119,
      "price_usd": 0.12364957229066255,
      "market_cap_usd": 222569230.12319258,
      "spot_volume_24h_usd": 35417456.7909694,
      "percent_change_7d": 9.54426306
    },
    {
      "symbol": "JASMY",
      "name": "JasmyCoin",
      "rank": 120,
      "price_usd": 0.004440178751169127,
      "market_cap_usd": 219544636.91813272,
      "spot_volume_24h_usd": 13935011.28217789,
      "percent_change_7d": 0.95591274
    },
    {
      "symbol": "KAIA",
      "name": "Kaia",
      "rank": 121,
      "price_usd": 0.03436461850374994,
      "market_cap_usd": 218883872.51897642,
      "spot_volume_24h_usd": 4794463.83858107,
      "percent_change_7d": -1.35399722
    },
    {
      "symbol": "VELVET",
      "name": "Velvet",
      "rank": 122,
      "price_usd": 0.5142026290363269,
      "market_cap_usd": 216513405.51320225,
      "spot_volume_24h_usd": 9280934.71039211,
      "percent_change_7d": 30.67564479
    },
    {
      "symbol": "ZBCN",
      "name": "Zebec Network",
      "rank": 123,
      "price_usd": 0.0021325625082306127,
      "market_cap_usd": 213253639.27481756,
      "spot_volume_24h_usd": 10406180.04259302,
      "percent_change_7d": -3.68603524
    },
    {
      "symbol": "FLOKI",
      "name": "FLOKI",
      "rank": 124,
      "price_usd": 2.1801976491856532e-05,
      "market_cap_usd": 208575436.1524373,
      "spot_volume_24h_usd": 14938980.40160312,
      "percent_change_7d": -4.09215519
    },
    {
      "symbol": "EIGEN",
      "name": "EigenCloud",
      "rank": 125,
      "price_usd": 0.2392230617429932,
      "market_cap_usd": 197286479.08853692,
      "spot_volume_24h_usd": 26896890.99524566,
      "percent_change_7d": -4.15683703
    },
    {
      "symbol": "TEL",
      "name": "Telcoin",
      "rank": 126,
      "price_usd": 0.002028915786688676,
      "market_cap_usd": 194926555.5708669,
      "spot_volume_24h_usd": 911234.44557279,
      "percent_change_7d": -11.33141895
    },
    {
      "symbol": "STRK",
      "name": "Starknet",
      "rank": 127,
      "price_usd": 0.028303062604115387,
      "market_cap_usd": 190958996.18491754,
      "spot_volume_24h_usd": 15823530.1470565,
      "percent_change_7d": -7.37665387
    },
    {
      "symbol": "FF",
      "name": "Falcon Finance",
      "rank": 128,
      "price_usd": 0.06391207751989215,
      "market_cap_usd": 189818870.2340797,
      "spot_volume_24h_usd": 55067639.8651133,
      "percent_change_7d": 7.19443871
    },
    {
      "symbol": "GRT",
      "name": "The Graph",
      "rank": 129,
      "price_usd": 0.017238658208603225,
      "market_cap_usd": 187755599.62004873,
      "spot_volume_24h_usd": 11630654.77387526,
      "percent_change_7d": -1.65703997
    },
    {
      "symbol": "H",
      "name": "Humanity",
      "rank": 130,
      "price_usd": 0.0595779642623283,
      "market_cap_usd": 184608942.0340114,
      "spot_volume_24h_usd": 10965168.62105399,
      "percent_change_7d": -11.9958029
    },
    {
      "symbol": "RAY",
      "name": "Raydium",
      "rank": 131,
      "price_usd": 0.6818447992432016,
      "market_cap_usd": 183630276.95176217,
      "spot_volume_24h_usd": 12729573.76324244,
      "percent_change_7d": 0.45777335
    },
    {
      "symbol": "PIEVERSE",
      "name": "Pieverse",
      "rank": 132,
      "price_usd": 0.6609272022099894,
      "market_cap_usd": 178848368.17641205,
      "spot_volume_24h_usd": 8844139.07972774,
      "percent_change_7d": -2.00438765
    },
    {
      "symbol": "CHZ",
      "name": "Chiliz",
      "rank": 133,
      "price_usd": 0.01654739414629083,
      "market_cap_usd": 174656662.43536374,
      "spot_volume_24h_usd": 34153053.20990212,
      "percent_change_7d": -2.81340204
    },
    {
      "symbol": "ENS",
      "name": "Ethereum Name Service",
      "rank": 134,
      "price_usd": 4.256952724424084,
      "market_cap_usd": 174477397.02366248,
      "spot_volume_24h_usd": 16046306.32975714,
      "percent_change_7d": 3.97073211
    },
    {
      "symbol": "COMP",
      "name": "Compound",
      "rank": 135,
      "price_usd": 17.43677354294581,
      "market_cap_usd": 174367735.42713693,
      "spot_volume_24h_usd": 11390210.13879036,
      "percent_change_7d": 2.75145662
    },
    {
      "symbol": "AXS",
      "name": "Axie Infinity",
      "rank": 136,
      "price_usd": 0.9999145527110974,
      "market_cap_usd": 174197439.03047925,
      "spot_volume_24h_usd": 19477284.61933284,
      "percent_change_7d": -0.67701511
    },
    {
      "symbol": "KAITO",
      "name": "KAITO",
      "rank": 137,
      "price_usd": 0.71089453447308,
      "market_cap_usd": 171602041.872629,
      "spot_volume_24h_usd": 37143961.4746554,
      "percent_change_7d": 2.72515472
    },
    {
      "symbol": "AKT",
      "name": "Akash Network",
      "rank": 138,
      "price_usd": 0.5751602534457733,
      "market_cap_usd": 170145497.040598,
      "spot_volume_24h_usd": 3607142.55977019,
      "percent_change_7d": -1.65868582
    },
    {
      "symbol": "IOTA",
      "name": "IOTA",
      "rank": 139,
      "price_usd": 0.0356415025423699,
      "market_cap_usd": 161785511.63767582,
      "spot_volume_24h_usd": 7161718.6116211,
      "percent_change_7d": -3.4962967
    },
    {
      "symbol": "TWT",
      "name": "Trust Wallet Token",
      "rank": 140,
      "price_usd": 0.35712762462575115,
      "market_cap_usd": 153515064.8066308,
      "spot_volume_24h_usd": 7275917.46113465,
      "percent_change_7d": 4.7761265
    },
    {
      "symbol": "MX",
      "name": "MX Token",
      "rank": 141,
      "price_usd": 1.660021567264644,
      "market_cap_usd": 152451955.12008658,
      "spot_volume_24h_usd": 7139207.55064425,
      "percent_change_7d": 0.58935116
    },
    {
      "symbol": "WIF",
      "name": "dogwifhat",
      "rank": 142,
      "price_usd": 0.15172804949984767,
      "market_cap_usd": 151551888.3157393,
      "spot_volume_24h_usd": 49947595.66987422,
      "percent_change_7d": -3.89618966
    },
    {
      "symbol": "APE",
      "name": "ApeCoin",
      "rank": 143,
      "price_usd": 0.15134888812046707,
      "market_cap_usd": 151348888.12046707,
      "spot_volume_24h_usd": 25354345.97753696,
      "percent_change_7d": -7.27438279
    },
    {
      "symbol": "EDGE",
      "name": "edgeX",
      "rank": 144,
      "price_usd": 0.42428062603900535,
      "market_cap_usd": 148498219.11365187,
      "spot_volume_24h_usd": 15304684.01831611,
      "percent_change_7d": 1.77068488
    },
    {
      "symbol": "THETA",
      "name": "Theta Network",
      "rank": 145,
      "price_usd": 0.148359990163526,
      "market_cap_usd": 148359990.163526,
      "spot_volume_24h_usd": 7823638.60545148,
      "percent_change_7d": 8.26351254
    },
    {
      "symbol": "FARTCOIN",
      "name": "Fartcoin",
      "rank": 146,
      "price_usd": 0.14478304853528057,
      "market_cap_usd": 144782796.03364393,
      "spot_volume_24h_usd": 15245607.31994845,
      "percent_change_7d": 0.69295333
    },
    {
      "symbol": "XCN",
      "name": "Onyxcoin",
      "rank": 147,
      "price_usd": 0.0036672120411767924,
      "market_cap_usd": 142440775.70045653,
      "spot_volume_24h_usd": 6229889.46129134,
      "percent_change_7d": -3.77385461
    },
    {
      "symbol": "SAND",
      "name": "The Sandbox",
      "rank": 148,
      "price_usd": 0.0482493737400818,
      "market_cap_usd": 141739275.9135131,
      "spot_volume_24h_usd": 12754783.83038475,
      "percent_change_7d": -2.41078828
    },
    {
      "symbol": "RUNE",
      "name": "THORChain",
      "rank": 149,
      "price_usd": 0.4179075192576227,
      "market_cap_usd": 141354443.90087053,
      "spot_volume_24h_usd": 4533190.28642089,
      "percent_change_7d": 7.33376686
    },
    {
      "symbol": "MANA",
      "name": "Decentraland",
      "rank": 150,
      "price_usd": 0.069782858955154,
      "market_cap_usd": 138582447.17907315,
      "spot_volume_24h_usd": 9358276.80133203,
      "percent_change_7d": -4.14054575
    }
  ]
}